<annotation>
    <folder>Barricadas e inicidentes</folder>
    <filename>Image_38.jpg</filename>
    <size>
        <width>600</width>
        <height>323</height>
        <depth>3</depth>
    </size>
    <object>
        <name>Asalto</name>
        <pose>Unspecified</pose>
        <truncated>0</truncated>
        <occluded>0</occluded>
        <difficult>0</difficult>
        <polygon>
            <x1>463.113922</x1>
            <y1>125.542907</y1>
            <x2>463.113922</x2>
            <y2>125.542907</y2>
            <x3>529.834128</x3>
            <y3>130.029542</y3>
            <x4>528.289416</x4>
            <y4>146.739876</y4>
            <x5>461.489424</x5>
            <y5>141.443986</y5>
            <x6>462.964618</x6>
            <y6>125.333729</y6>
        </polygon>
        <bndbox>
            <xmin>461.489410</xmin>
            <ymin>125.333733</ymin>
            <xmax>529.834106</xmax>
            <ymax>146.739883</ymax>
        </bndbox>
    </object>
</annotation>